qaviton_log/__init__.py
qaviton_log/logger.py
qaviton_log-2019.11.13.14.45.27.510212.dist-info/LICENSE
qaviton_log-2019.11.13.14.45.27.510212.dist-info/METADATA
qaviton_log-2019.11.13.14.45.27.510212.dist-info/WHEEL
qaviton_log-2019.11.13.14.45.27.510212.dist-info/top_level.txt
qaviton_log-2019.11.13.14.45.27.510212.dist-info/RECORD
