Metadata-Version: 2.1
Name: qaviton-log
Version: 2019.11.13.14.45.27.510212
Summary: qaviton log
Home-page: https://github.com/qaviton/qaviton_log
Author: yehonadav
Author-email: qaviton@gmail.com
License: apache-2.0
Platform: UNKNOWN
Classifier: Programming Language :: Python :: 3.6
